{
  "mintAddress": "CmbdvB243nG4TEKjGPx7iGGXT4b5mFpynQUghKqF4ENu",
  "mintKeypair": [
    152,
    211,
    118,
    31,
    115,
    227,
    251,
    178,
    170,
    8,
    38,
    25,
    169,
    41,
    33,
    212,
    202,
    205,
    242,
    26,
    145,
    150,
    41,
    76,
    0,
    253,
    238,
    199,
    103,
    109,
    154,
    117,
    174,
    221,
    70,
    128,
    159,
    86,
    13,
    246,
    178,
    247,
    91,
    113,
    159,
    184,
    78,
    32,
    93,
    184,
    129,
    134,
    49,
    188,
    148,
    133,
    66,
    106,
    113,
    227,
    84,
    17,
    0,
    162
  ],
  "mintAuthority": "Gmhpm85fByXJ3UQH7LqJkibW2bGLz5Diatute2YNM7ny",
  "decimals": 6,
  "programId": "2dwpmEaGB8euNCirbwWdumWUZFH3V91mbPjoFbWT24An",
  "signature": "54uACp2Z8NRgCEw6rUPChCSSDHXuwMSovPW8D1n4S3JEaCDE3jGkDqQV2bnwQfFYZrWSXLgFZJowBMciEsJh9oPv",
  "metadata": {
    "name": "GorbChain Demo Token",
    "symbol": "GDEMO",
    "description": "A demonstration Token-2022 on GorbChain with advanced features",
    "decimals": 6,
    "totalSupply": 1200,
    "creator": "GorbChain Labs",
    "category": "Utility",
    "features": [
      "Extensible",
      "Upgradeable",
      "Metadata Support"
    ],
    "createdAt": "2025-06-26T23:10:55.766Z",
    "network": "GorbChain",
    "version": "2022"
  },
  "extensions": [],
  "createdAt": "2025-06-26T23:10:57.737Z",
  "type": "token-2022-demo"
}